xray_sdk/__init__.py
xray_sdk/client.py
xray_sdk/run.py
xray_sdk/step.py
xray_sdk-0.1.3.dist-info/METADATA
xray_sdk-0.1.3.dist-info/WHEEL
xray_sdk-0.1.3.dist-info/top_level.txt
xray_sdk-0.1.3.dist-info/RECORD
