Metadata-Version: 2.4
Name: xray-sdk
Version: 0.1.3
Summary: Lightweight debugging SDK for multi-step AI pipelines.
Author: Equal Collective
License: Proprietary
Requires-Python: >=3.9
Requires-Dist: requests>=2.31.0
